data_seeder/__init__.py
data_seeder/admin.py
data_seeder/apps.py
data_seeder/base.py
data_seeder/generators.py
data_seeder/management/__init__.py
data_seeder/management/commands/__init__.py
data_seeder/management/commands/seeddata.py
data_seeder/templates/admin/data_generator/change_list.html
data_seeder/templates/admin/data_generator/generate_form.html
django_data_seeder-0.2.0.dist-info/DESCRIPTION.rst
django_data_seeder-0.2.0.dist-info/METADATA
django_data_seeder-0.2.0.dist-info/RECORD
django_data_seeder-0.2.0.dist-info/WHEEL
django_data_seeder-0.2.0.dist-info/metadata.json
django_data_seeder-0.2.0.dist-info/top_level.txt
tests/__init__.py
tests/models.py
tests/test_base.py
tests/test_generators.py
tests/test_settings.py
