Metadata-Version: 2.0
Name: django-data-seeder
Version: 0.2.0
Summary: A data seeder for models for Django.
Home-page: https://github.com/kbernst30/django-data-seeder/
Author: Kyle Bernstein
Author-email: kbernst30@gmail.com
License: BSD-3-Clause
Platform: UNKNOWN
Classifier: Environment :: Web Environment
Classifier: Framework :: Django
Classifier: Framework :: Django :: 2.2
Classifier: Intended Audience :: Developers
Classifier: License :: OSI Approved :: BSD License
Classifier: Operating System :: OS Independent
Classifier: Programming Language :: Python
Classifier: Programming Language :: Python :: 3.6
Classifier: Topic :: Internet :: WWW/HTTP
Classifier: Topic :: Internet :: WWW/HTTP :: Dynamic Content
